MANIFEST.in
setup.cfg
setup.py
jsoncat/__init__.py
jsoncat/runner.py
jsoncat.egg-info/PKG-INFO
jsoncat.egg-info/SOURCES.txt
jsoncat.egg-info/dependency_links.txt
jsoncat.egg-info/entry_points.txt
jsoncat.egg-info/top_level.txt