Metadata-Version: 1.1
Name: jsoncat
Version: 0.1.0
Summary: Simple way of print json files
Home-page: https://github.com/hurrycane/jsoncat
Author: Bogdan Gaza
Author-email: bc.gaza@gmail.com
License: UNKNOWN
Keywords: jsoncat,json,cat,print,pretty
Platform: any
Classifier: Topic :: System :: Distributed Computing
Classifier: Topic :: Software Development :: Libraries
Classifier: License :: OSI Approved :: MIT License
Classifier: Topic :: Database :: Front-Ends
